Metadata-Version: 1.2
Name: dirtyclean
Version: 0.1
Summary: get rid of unicode punctuation and other garbage from strings
Home-page: https://github.com/paultopia/dirtyclean
Author: Paul Gowder
Author-email: paul.gowder@gmail.com
License: MIT
Keywords: textmining,nlp,datacleaning
Platform: UNKNOWN
Classifier: Development Status :: 3 - Alpha
Classifier: Intended Audience :: Developers
Classifier: Intended Audience :: Science/Research
Classifier: License :: OSI Approved :: MIT License
Classifier: Programming Language :: Python :: 3 :: Only
Requires-Python: >=3
